easy/__init__.py
easy/base/__init__.py
easy/base/model_base.py
easy/base/mysql_base.py
easy/base/mysql_base_092.py
easy/base/peewee_custom.py
easy/base/service_base.py
easy/base/service_hooks.py
easy/base/sqlite3_base.py
easy/utils/__init__.py
easy/utils/dateUtil.py
easy/utils/jsonUtil.py
easy/utils/local_storage.py
easy/utils/netUtil.py
easy/utils/randomUtil.py
pytest_salt/__init__.py
pytest_salt/case.py
pytest_salt/plugin.py
pytest_salt/salt.py
scripts/__init__.py
scripts/py_codegen/__init__.py
scripts/py_codegen/py_codegen_v2.py
ease_test-0.1.5.dist-info/METADATA
ease_test-0.1.5.dist-info/WHEEL
ease_test-0.1.5.dist-info/entry_points.txt
ease_test-0.1.5.dist-info/top_level.txt
ease_test-0.1.5.dist-info/RECORD
